netlify_deployer/__init__.py
netlify_deployer/__main__.py
netlify_deployer-0.5.2.dist-info/AUTHORS
netlify_deployer-0.5.2.dist-info/LICENSE
netlify_deployer-0.5.2.dist-info/METADATA
netlify_deployer-0.5.2.dist-info/WHEEL
netlify_deployer-0.5.2.dist-info/entry_points.txt
netlify_deployer-0.5.2.dist-info/pbr.json
netlify_deployer-0.5.2.dist-info/top_level.txt
netlify_deployer-0.5.2.dist-info/RECORD
