Metadata-Version: 2.1
Name: netlify-deployer
Version: 0.5.2
Summary: Package to help with deploying Netlify
Home-page: https://github.com/cyplo/netlify_deployer
Author: Cyryl Płotnicki
Author-email: cyplo@cyplo.net
License: UNKNOWN
Platform: UNKNOWN
Classifier: Programming Language :: Python :: 3
Classifier: License :: OSI Approved :: MIT License
Classifier: Operating System :: OS Independent
Requires-Python: >=3.6
Requires-Dist: requests
